LICENSE
MANIFEST.in
README.rst
requirements.txt
setup.py
bin/fzsl
etc/fzsl.bash
etc/fzsl.conf
fzsl/__init__.py
fzsl/core.py
fzsl/scanner.py
fzsl/ui.py
fzsl.egg-info/PKG-INFO
fzsl.egg-info/SOURCES.txt
fzsl.egg-info/dependency_links.txt
fzsl.egg-info/requires.txt
fzsl.egg-info/top_level.txt
test/test_core.py
test/test_scanner.py