Metadata-Version: 1.1
Name: fzsl
Version: 0.4
Summary: Fuzzy path searching for shells
Home-page: http://github.com/jsbronder/fzsl
Author: Justin Bronder
Author-email: jsbronder@gmail.com
License: BSD
Keywords: fuzzy shell search console match ncurses
Platform: UNKNOWN
Classifier: Development Status :: 3 - Alpha
Classifier: Environment :: Console
Classifier: Environment :: Console :: Curses
Classifier: Intended Audience :: Developers
Classifier: Intended Audience :: End Users/Desktop
Classifier: Intended Audience :: System Administrators
Classifier: License :: OSI Approved :: BSD License
Classifier: Operating System :: POSIX
Classifier: Programming Language :: Python
Classifier: Programming Language :: Python :: 2
Classifier: Programming Language :: Python :: 2.7
Classifier: Programming Language :: Python :: 3
Classifier: Programming Language :: Python :: 3.3
Classifier: Programming Language :: Python :: 3.4
Classifier: Topic :: System :: Shells
Classifier: Topic :: System :: Systems Administration
Classifier: Topic :: System :: System Shells
Classifier: Topic :: Terminals
Classifier: Topic :: Terminals :: Serial
Classifier: Topic :: Terminals :: Telnet
Classifier: Topic :: Terminals :: Terminal Emulators/X Terminals
Classifier: Topic :: Text Processing :: Filters
Classifier: Topic :: Utilities
